tensordata/__init__.py
tensordata/book/__init__.py
tensordata/book/_book.py
tensordata/cv/__init__.py
tensordata/cv/_caltech.py
tensordata/cv/_cifar.py
tensordata/cv/_coil.py
tensordata/cv/_mnist.py
tensordata/cv/_mnist_kannada.py
tensordata/cv/_mnist_kuzushiji.py
tensordata/cv/_mnist_tibetan.py
tensordata/cv/_stl10.py
tensordata/dm/__init__.py
tensordata/dm/_dm.py
tensordata/dm/_movielens.py
tensordata/gfile/__init__.py
tensordata/gfile/_gfile.py
tensordata/nlp/__init__.py
tensordata/nlp/chinese/__init__.py
tensordata/nlp/chinese/lexicon/__init__.py
tensordata/nlp/chinese/lexicon/_lexicon.py
tensordata/nlp/chinese/literature/__init__.py
tensordata/nlp/chinese/literature/_literature.py
tensordata/nlp/chinese/reviews/__init__.py
tensordata/nlp/chinese/reviews/_reviews.py
tensordata/nlp/chinese/stopword/__init__.py
tensordata/nlp/chinese/stopword/_stopword.py
tensordata/paper/__init__.py
tensordata/paper/_arxiv.py
tensordata/paper/CVPR/__init__.py
tensordata/paper/CVPR/_cvpr.py
tensordata/paper/ECCV/__init__.py
tensordata/paper/ECCV/_eccv.py
tensordata/paper/ICCV/__init__.py
tensordata/paper/ICCV/_iccv.py
tensordata/paper/WACV/__init__.py
tensordata/paper/WACV/_wacv.py
tensordata/report/__init__.py
tensordata/report/_china.py
tensordata/report/p2peye/__init__.py
tensordata/report/p2peye/_p2peye.py
tensordata/report/weather_china/__init__.py
tensordata/report/weather_china/_weather_china.py
tensordata/utils/__init__.py
tensordata/utils/_utils.py
tensordata/utils/compress/__init__.py
tensordata/utils/compress/_files_compress.py
tensordata/utils/compress/_folder_compress.py
tensordata/utils/compress/_un_compress.py
tensordata/utils/pip/__init__.py
tensordata/utils/pip/_pip.py
tensordata/utils/request/__init__.py
tensordata/utils/request/_download.py
tensordata-0.4.2.dist-info/LICENSE.txt
tensordata-0.4.2.dist-info/METADATA
tensordata-0.4.2.dist-info/WHEEL
tensordata-0.4.2.dist-info/top_level.txt
tensordata-0.4.2.dist-info/RECORD
