Metadata-Version: 2.1
Name: tensordata
Version: 0.4.2
Summary: CV, NLP, DM datasets Toolkit for Machine Learning.
Home-page: https://github.com/Hourout/tensordata
Author: JinQing Lee
Author-email: hourout@163.com
License: Apache License Version 2.0
Keywords: computer-vision,natural-language-processing,data-mining,Machine-Learning,datasets
Platform: UNKNOWN
Classifier: Intended Audience :: Developers
Classifier: Intended Audience :: Education
Classifier: Intended Audience :: Science/Research
Classifier: Topic :: Scientific/Engineering
Classifier: Topic :: Scientific/Engineering :: Artificial Intelligence
Classifier: Topic :: Scientific/Engineering :: Visualization
Classifier: License :: OSI Approved :: Apache Software License
Classifier: Programming Language :: Python :: 3.6
Classifier: Programming Language :: Python :: 3.7
Classifier: Programming Language :: Python :: 3.8
Classifier: Programming Language :: Python :: 3.9
Requires-Dist: linora (>=1.0.0)
Requires-Dist: rarfile
Requires-Dist: requests
